<?xml version="1.0" encoding="utf-8"?>
<GameData>
	<Language_ZH_Hant_HK>
		<Row Tag="TXT_KEY_PROCESS_CULTURE">
			<Text>藝術</Text>
		</Row>
		<Row Tag="TXT_KEY_PROCESS_CULTURE_HELP">
			<Text>[COLOR_POSITIVE_TEXT]藝術[ENDCOLOR]將 25% 此城市的[ICON_PRODUCTION]產能轉化為[ICON_CULTURE]文化，同時減少[ICON_CULTURE]文化乏味 25%。</Text>
		</Row>
		<Row Tag="TXT_KEY_PROCESS_CULTURE_STRATEGY">
			<Text>在藝術上投資生產是提升您的文明文化產出的好方法，無論是為了搶下一個政策或是為了避免他人旅遊的勝利。也可以減少文化乏味。</Text>
		</Row>

		<Row Tag="TXT_KEY_PROCESS_DEFENSE">
			<Text>防禦</Text>
		</Row>
		<Row Tag="TXT_KEY_PROCESS_DEFENSE_HELP">
			<Text>[COLOR_POSITIVE_TEXT]防禦[ENDCOLOR]提升城市的[ICON_STRENGTH]防禦，並增加城市[ICON_PRODUCTION]產能 10% 的生命恢復。</Text>
		</Row>
		<Row Tag="TXT_KEY_PROCESS_DEFENSE_STRATEGY">
			<Text>將生產投資在防衛上，是避免您的城市被外國勢力征服的最後方法。</Text>
		</Row>

		<Row Tag="TXT_KEY_PROCESS_FOOD">
			<Text>農業</Text>
		</Row>
		<Row Tag="TXT_KEY_PROCESS_FOOD_HELP">
			<Text>[COLOR_POSITIVE_TEXT]農業[ENDCOLOR]將 25% 此城市的[ICON_PRODUCTION]產能轉化為[ICON_FOOD]食物，同時減少[ICON_FOOD]和[ICON_PRODUCTION]窘迫 25%。</Text>
		</Row>
		<Row Tag="TXT_KEY_PROCESS_FOOD_STRATEGY">
			<Text>將生產投資在農業上是提升城市成長的好方法，如果您有比市民更多的生產單元格，或是您想要長期有更多的專家，這會很有用。也可以減少生產窘迫。</Text>
		</Row>

		<Row Tag="TXT_KEY_PROCESS_TOURISM">
			<Text>宣傳</Text>
		</Row>
		<Row Tag="TXT_KEY_PROCESS_TOURISM_HELP">
			<Text>[COLOR_POSITIVE_TEXT]宣傳[ENDCOLOR]將 15% 此城市的[ICON_PRODUCTION]產能轉化爲[ICON_TOURISM]旅遊業績。[NEWLINE][NEWLINE]需已解鎖社會主義現實主義政策。</Text>
		</Row>
		<Row Tag="TXT_KEY_PROCESS_TOURISM_STRATEGY">
			<Text>{TXT_KEY_PROCESS_TOURISM_HELP}[NEWLINE][NEWLINE]將生產投資在宣傳上是提升您的城市在世界上影響力的好方法，如果您目前正處於革命浪潮中，或是您想迫使其他文明經歷革命浪潮，這將會非常有用。</Text>
		</Row>

		<Row Tag="TXT_KEY_PROCESS_TREASURE_FLEET">
			<Text>寶藏艦隊</Text>
		</Row>
		<Row Tag="TXT_KEY_PROCESS_TREASURE_FLEET_HELP">
			<Text>將這個城市的[ICON_PRODUCTION]產能貢獻給寶藏艦隊計劃。成本會根據遊戲中玩家的數量和目前的時代而增加。</Text>
		</Row>

		<Row Tag="TXT_KEY_PROCESS_WARGAMES">
			<Text>全球戰爭遊戲</Text>
		</Row>
		<Row Tag="TXT_KEY_PROCESS_WARGAMES_HELP">
			<Text>將這個城市的[ICON_PRODUCTION]產能貢獻給全球戰爭遊戲計劃。成本會根據遊戲中玩家的數量和目前的時代而增加。</Text>
		</Row>

		<Row Tag="TXT_KEY_PROCESS_UNITED_NATIONS">
			<Text>聯合國</Text>
		</Row>
		<Row Tag="TXT_KEY_PROCESS_UNITED_NATIONS_HELP">
			<Text>將這個城市的[ICON_PRODUCTION]產能貢獻給聯合國計劃。成本會根據遊戲中玩家的數量和目前的時代而增加。</Text>
		</Row>
	</Language_ZH_Hant_HK>
</GameData>